pluginlab_admin/__init__.py
pluginlab_admin/app.py
pluginlab_admin/auth.py
pluginlab_admin/event.py
pluginlab_admin/monetization.py
pluginlab_admin/token_verifier.py
pluginlab_admin/webhook.py
pluginlab_admin-0.4.1.dist-info/METADATA
pluginlab_admin-0.4.1.dist-info/WHEEL
pluginlab_admin-0.4.1.dist-info/RECORD
