Metadata-Version: 2.1
Name: pluginlab_admin
Version: 0.4.1
Summary: 
Author: Aurélien Brabant
Author-email: main@aurelienbrabant.fr
Requires-Python: >=3.11,<4.0
Classifier: Programming Language :: Python :: 3
Classifier: Programming Language :: Python :: 3.11
Requires-Dist: pyjwt[crypto] (>=2.8.0,<3.0.0)
Requires-Dist: requests (>=2.31.0,<3.0.0)
